mutuple.abi3.so
mutuple-1.0.0.dist-info/METADATA
mutuple-1.0.0.dist-info/LICENSE
mutuple-1.0.0.dist-info/RECORD
mutuple-1.0.0.dist-info/top_level.txt
mutuple-1.0.0.dist-info/WHEEL
